{"North Cape":18.6,"Rangaunu Harbour":22.5,"Karikari Peninsula":22.9,"Tangonge":21.1,"Ahipara":8.5,"Paihia":28.2,"Mataraua Forest":9.1,"Matawaia-Taumarere":16.3,"Russell Peninsula":75,"Opua (Far North District)":51.2,"Russell Forest-Rawhiti":10.5,"Moerewa":2.9,"Maromaku":36,"Kauri":58.2,"Maungatapere":64.5,"Kamo West":54.1,"Matapouri-Tutukaka":63.9,"Kiripaka":69.2,"Kamo East":38.8,"Maunu":55.7,"Horahora":39.6,"Woodhill-Vinetown":35.4,"Whangarei Central":43.5,"Riverside":49.1,"Raumanga":21.7,"Morningside (Whangarei District)":37,"Ngunguru":63.3,"Otaika-Portland":56.8,"Oakleigh-Mangapai":68.5,"Pataua":66.7,"Mangawhai Rural":70.6,"Mangawhai Heads":63.4,"Mangawhai":78.8,"Okahukura Peninsula":61.3,"Cape Rodney":67.9,"South Head":66,"Kaipara Hills":65.8,"Dome Valley-Matakana":67.6,"Warkworth West":65.9,"Puhoi Valley":72,"Warkworth East":55.2,"Sandspit":84.4,"Tawharanui Peninsula":78.5,"Henderson Valley":62,"Bucklands Beach South":36.4,"Upper Clutha Valley":71.4,"Kingston":78.9,"Waipapa":63,"Puketotara":60.2,"Waima Forest":2.9,"Helensville Rural":74.2,"Helensville":60.3,"Waikoukou Valley":82.1,"Stillwater":75,"Waimauku":69.8,"Vipond":74.5,"Muriwai":73.3,"Kumeu-Huapai South":59,"Gulf Harbour North":70,"Manly East":69.6,"Riverhead":66.1,"Army Bay":73.8,"Kumeu Rural East":58.4,"Gulf Harbour South":69.1,"Paremoremo West":75.9,"Taupaki":70.6,"Long Bay":51,"Paremoremo East":54,"Albany Heights":39.4,"Whenuapai":59.4,"Whenuapai West":37.8,"Waitakere Ranges North":71,"Halfway Bush":71.4,"Brockville":53.2,"Riverview":58.7,"Waipoua Forest":21.7,"Torbay West":68.8,"Torbay East":75,"Albany Central":27.7,"Albany West":34.9,"Waiake":65.4,"Albany South":37.1,"Browns Bay Central":59.1,"Schnapper Rock":41.8,"Browns Bay South East":48.8,"Greenhithe West":74.6,"Rothesay Bay":66.1,"Greenhithe East":49.7,"Hobsonville":44.2,"Greenhithe South":56.4,"Onekawa Central":52.2,"Windsor Park":30.5,"Massey Central":21.1,"West Harbour Luckens Point":44,"Swanson Rural":61.6,"Glenfield Central":30.2,"Sunnynook North":40.8,"Bayview West (Auckland)":50.3,"Beach Haven West":53.6,"Swanson":29.9,"Bayview South (Auckland)":40.2,"Campbells Bay":68.1,"Royal Heights South":23.5,"Beach Haven East":30.2,"Massey Keegan":17.5,"Birkdale North":35.6,"Massey South":22.9,"Ranui North":14.1,"Te Atatu Peninsula North West":35.4,"Glenfield South West":37.1,"Forrest Hill West":33,"Castor Bay North":66.2,"Castor Bay South":63.8,"Beach Haven South":60.7,"Piha":72.2,"Henderson Larnoch":14.3,"Birkdale South":45.8,"Ranui South East":14.2,"Te Atatu Peninsula East":35.4,"Milford West":55,"Henderson Lincoln South":17.3,"Milford Central":66.3,"Chatswood":49.5,"Te Atatu South-Edmonton":24.2,"Takapuna West":45.9,"Henderson West":25.3,"Takapuna Central":53.1,"Northcote Central (Auckland)":37.5,"Akoranga":35.1,"Birkenhead South":76,"Henderson Central":22.2,"Homai East":8.6,"Glendene North West":24,"Glendene North East":15.1,"Sunnyvale West-Parrs Park":13.7,"Sunnyvale East":23.4,"Point Chevalier West":50,"Belmont (Auckland)":56,"Bayswater":62.5,"Glendene South":20.5,"Herne Bay":76,"Westmere North":66.4,"Point Chevalier North":72.1,"Point Chevalier East":55.7,"Oratia":74.8,"Saint Marys Bay":74.6,"Westmere South-Western Springs":65,"Kelston North":11,"Avondale Rosebank (Auckland)":14.1,"Narrow Neck":70.5,"Waterview":34.6,"Stanley Point":67.7,"Avondale West (Auckland)":12.3,"Eden Park":61.3,"Freemans Bay":66.4,"College Hill":61.7,"Mount Albert West":37.3,"Mount Albert North":41.7,"New Lynn South":29.1,"Fruitvale":23.7,"New Lynn Central":21.6,"Queen Street South West":32,"Karangahape West":52.9,"Avondale South (Auckland)":18.3,"Owairaka West":29,"New Windsor North":17.2,"Titirangi South":74.2,"Blockhouse Bay North":16.9,"Parnell East":62.4,"Laingholm":78.9,"Green Bay South":53.7,"Clarks Beach":45.6,"Clendon Park West":4,"Karaka Creek":67.6,"Rowandale West":3.3,"Weymouth East":2.8,"Mount Eden West":55.7,"Newmarket Park":46.3,"Blockhouse Bay South":30.6,"Orakei West":57.2,"Maungawhau":58.4,"Remuera West":55,"Mount Roskill West":16.2,"Remuera Waitaramoa":60.7,"Orakei East":38.1,"Lynfield Harbour View":34.5,"Mission Bay":65,"Mission Bay Eastridge":58.9,"Greenlane Central":50.3,"Remuera East":70.5,"Weymouth South":6,"Waldronville":66.7,"Port Chalmers":70.2,"Kerikeri Central":43.5,"Kerikeri South":66.3,"Royal Oak West (Auckland)":37.7,"Saint Heliers West":68.9,"Saint Heliers North":75.7,"Remuera Abbotts Park":54.7,"Hillsborough South (Auckland)":39.5,"Mount Wellington Hamlin":19.9,"Half Moon Bay West":56.2,"Auckland Airport":11.6,"Eastern Beach":43.7,"Sunnyhills West":40.8,"Tuapeka":84,"Greenlane South":45.7,"Glendowie North":75.7,"Onehunga West":42.9,"Oneroa West":60.9,"Glendowie South East":57.9,"Onehunga-Te Papapa Industrial":22.7,"Glen Innes East-Wai O Taiki Bay":25.1,"Penrose":30.4,"Mangere Bridge Ambury":29.8,"Point England North":12.4,"Bucklands Beach North":51.7,"Mangere Bridge":19.9,"Oneroa East-Palm Beach":69.6,"Tamaki East":17.9,"Panmure East":23.6,"Mount Wellington Central":25.7,"Pakuranga North":27.7,"Favona North":2,"Farm Cove":54.5,"Mount Wellington South West":22.3,"Favona East":3.6,"Mount Wellington South East":9.4,"Otahuhu Industrial":0,"Pakuranga Central":23.3,"Awhitu":60.2,"Otahuhu North West":3,"Howick West":40.7,"Mellons Bay":59,"Pakuranga Heights East":24.9,"Sutton Park":1.2,"Onetangi":68.2,"Howick Central":47.3,"Clinton":73.7,"Clutha Valley":72,"Massey Road North":4.1,"Massey Road South":2.5,"Cockle Bay":70,"Otara West":0.7,"Shelly Park":63.8,"Otara Central":1.3,"Papatoetoe West":4.2,"Sunkist Bay":76.3,"Manukau Central":10.6,"Goodwood Heights East":13.3,"Clendon Park North":2.6,"Papatoetoe East":4,"Papatoetoe South":3.6,"Te Puru":68.6,"Turanga":63.5,"Rongomai East":2.2,"Mission Heights South":8.2,"Burbank":2.9,"Bruce":68.1,"Manurewa East":5.4,"Manurewa West":4.9,"Randwick Park East":7.6,"Wattle Downs West":28.7,"Wattle Downs North":5.2,"Wattle Downs East":22.2,"Takanini East":8.4,"Takanini Central":13.8,"Ardmore":47,"Glenbrook":60.9,"Kawakawa Bay-Orere":69.2,"Papakura West":22.5,"Clevedon":71.7,"Karaka Lakes":27.3,"Patumahoe Rural":64.7,"Drury West":25.8,"Drury East":36.8,"Tamakae":61.3,"Hamilton Estate":52.7,"Ramarama":58.8,"Greensboro":38.7,"Rooseville Park":54.9,"Cloverlea (Auckland)":58.4,"Ararimu":74.1,"Waihi East":57.4,"Waihi South":45.4,"Aka Aka":69.7,"Mangatangi":54,"Tuakau Rural":58.1,"Tuakau North":44.2,"Onewhero":57.8,"Pokeno Rural":64.6,"Port Waikato-Waikaretu":39,"Pukekawa":67,"Maramarua":57.4,"Whangamarino":42.7,"Te Akau":61.7,"Hamilton East Cook":41.4,"Hamilton East":54.9,"Melville South":29.5,"Bader":23.3,"Silverdale (Hamilton City)":45.8,"Glenview":41.8,"Pokuru":75.3,"Te Kauwhata East":41.8,"Huntly Rural":54.4,"Waerenga":75.5,"Huntly West":9.9,"Huntly East":30.3,"Huntly South":34.1,"Raglan":55.2,"Whitikahu":64.6,"Horsham Downs":67.9,"Whatawhata East":60.2,"Hamilton Park":68.3,"Tamahere North":68.3,"Tamahere West":67.4,"Pukemoremore":62.1,"Tamahere South":77.6,"Tahuna-Mangateparu":72.5,"Mangaiti":62,"Tatuanui":62.2,"Tahuroa":69.1,"Morrinsville East":64.3,"Te Poi":71.2,"Flagstaff South":50.6,"Rototuna North":31.1,"Rototuna South West":54.5,"Rototuna South East":54.4,"Hautapu":74.4,"Karapiro":79.1,"Saint Andrews West":39.7,"Huntington":54,"Chartwell":33.9,"Beerescourt":47.4,"Miropiko":54.5,"Maeroa":41.7,"Cambridge North":76.8,"Cambridge West":74.6,"Catlins":59.6,"Milton":67.2,"Waianiwa":71.4,"Riverton":52.2,"Fairfield South (Hamilton City)":37.3,"Whitiora":28.1,"Frankton Junction":33.8,"Ruakura":49.8,"Claudelands":42,"Tauranga Central":41.8,"Judea":47.2,"Omanu Beach":68.9,"Wallacetown":77.8,"Grove Bush":77.6,"Edendale-Woodlands":64.1,"Stewart Island":73.9,"Cambridge East":68.9,"Cambridge Park-River Garden":78.9,"Pukerimu":77.6,"Cambridge Central":76.9,"Leamington West":71.3,"Goodfellow Park":57.1,"Maungatautari":80.9,"Rotongata":62.9,"Pirongia Forest":30.6,"Honikiwi":63.3,"Te Kawa":76.1,"Otorohanga":34,"Maihiihi":68.3,"Puniu":52.3,"Tirau":67.7,"Putaruru Rural":63.9,"Putaruru":42.8,"Kinleith":55.6,"Parkdale":30.9,"Strathmore (South Waikato District)":20.8,"Tokoroa Central":21.2,"Moananui":22.3,"Herangi":41.7,"Hangatiki":49.4,"Aria":43.3,"Nukuhau":46.7,"Rangatira Park":53.2,"Taupo Central West":29.6,"Awarua Plains":63.5,"Tauhara":42,"Taupo Central East":33.8,"Bird Area":61.5,"Richmond Heights":53.6,"Wharewaka":66.7,"Waitahanui":33.3,"Turangi":16.5,"Waiau":41.2,"Victoria":12.8,"Pirimai West":50.9,"Wyndham-Catlins":67.8,"Omokoroa South":69,"Te Puna":51.4,"Rangiuru":38.2,"Te Puke South":33.1,"Maketu":16.2,"Pukehina Beach":46.7,"Pongakawa":51.6,"Matua North":73.8,"Mount Maunganui North":64.9,"Otumoetai East":62.2,"Brookfield East":53.5,"Mount Maunganui South":71.4,"Waikaka":74.4,"Tauranga Hospital":37.7,"Gate Pa":40.8,"Greerton South":48.8,"Tauranga South":47.8,"Arataki North":55.7,"Greerton North":46.4,"Yatton Park":25.8,"Poraiti Hills":74.4,"Poraiti Flat":66.1,"Westshore":50,"Pyes Pa North":37.8,"Welcome Bay East":43.9,"Pacific View":65.3,"Palm Beach North":51.6,"Palm Beach South-Gravatt":64.3,"Papamoa Beach North":52.5,"Papamoa Beach South":60,"Motiti":65.3,"Rotoiti-Rotoehu":22.5,"Kawaha":33.6,"Pukehangi South":43.1,"Fordlands":7.5,"Kuirau":6.8,"Utuhina":27.2,"Pomare":47.7,"Rotorua Central":31.6,"Hillcrest (Rotorua District)":29.8,"Glenholme South":31.3,"Owhata West":28.8,"Holdens Bay-Rotokawa":28.6,"Owhata East":28.9,"Ngakuru":65.5,"Kaingaroa-Whakarewarewa":43.1,"Golden Springs":54.5,"Manawahe":58.3,"Thornton-Awakeri":48.4,"Coastlands":37.3,"Whakatane West":27.6,"Whakatane Central":27,"Wainui":17.5,"Ohope":67.3,"Galatea":23.4,"Marewa East":39.5,"Waimumu-Kaiwera":80.3,"Gore North":70,"Kawerau Central":16.4,"Waiotahe":29.4,"Cape Runaway":4.7,"Opotiki":10.7,"Otara-Tirohanga":22.7,"Oponae":20,"Te Hapara North":38.9,"Maungataniwha-Raupunga":27.5,"Frasertown-Ruakituri":33.3,"Whakaki":16.2,"Wairoa":8.3,"Mahia":11.3,"Puketitiri-Tutira":58.7,"Sherenden-Crownthorpe":80,"Maraekakaho":77.6,"Puketapu-Eskdale":72.3,"Lochain Park":16.4,"Aokautere Rural":72.2,"East Gore":66.3,"Flaxmere South":11.2,"Clive":61.3,"St Leonards":38.5,"Longlands-Pukahu":57.3,"Karamu":39.8,"Queens Square":45.5,"Mangateretere":67.7,"Haumoana":59.2,"Taradale South":65.6,"Bluff Hill":66.9,"Mangaroa":83.5,"Ohaeawai-Waimate North":34.8,"Puketona-Waitangi":55.4,"Hereworth":81.8,"Kahuranaki":68.5,"Bay View (Napier City)":59.2,"Onekawa South":34.1,"Meeanee-Awatoto":56.5,"Mangaonuku":62.7,"Makaretu":59.5,"Mangarara":66.4,"Waipukurau East":45.7,"Taurekaitai":63.9,"Spotswood":54.5,"Omata":65.4,"Oakura":72.1,"Kaitake":71.6,"Kawaroa":60.5,"New Plymouth Central":50,"Mangaoraka":79.6,"Tikorangi":63.2,"Everett Park":78.8,"Inglewood":72.1,"Tarata":80.8,"Pembroke":81.5,"Douglas":87.5,"Toko":85.3,"Ngapuhi":9.9,"Kaikohe":6.5,"Hawera Central":45,"Mangawhio":71.4,"Manutahi-Waitotora":57,"Patea":20,"Otangiwai-Ohura":59.6,"Ngapuke":36.4,"Taumarunui North":24.2,"Mowhanau":72.3,"Brunswick-Papaiti":72.9,"Castlecliff West":37.9,"Lower Aramoho":47.2,"Springvale West":54.1,"Upper Aramoho":54.5,"Laird Park":44.6,"Wembley Park":34.5,"Whanganui East-Williams Domain":54,"Cornmarket":37.2,"Whanganui East-Riverlands":54.5,"Kaitoke-Fordell":64.3,"Parewanui":75,"Bulls":58.8,"Kiwitea":77.8,"Tokorangi":70.6,"Oroua Downs":65.1,"Awahuri":73.3,"Pohangina-Apiti":75.9,"Taikorea":70.3,"Sandon":71.8,"Kimbolton North":62.1,"Gore Main":71.2,"Warwick":66.3,"Kimbolton West":58.1,"Kimbolton South":61.8,"Kauwhata":74.8,"Taonui":77.2,"Newbury":60.2,"Tremaine":30.4,"Whakarongo":69.9,"Westbrook":40,"Takaro North":53.5,"Maraetarata":57.1,"Turitea":51.8,"Linton Camp":50.3,"Ashhurst":62,"Aokautere":76.6,"Pihauatua":62.3,"Makomako":30.2,"Kawiu North":51,"Waiopehu":35.7,"Makahika":71.7,"Kimberley":77.3,"Otaki Beach":38.7,"Forest Lakes (Kapiti Coast District)":48,"Otaki":34.3,"Te Horo":75,"Waikanae Beach":71.4,"Peka Peka":87.5,"Paraparaumu Beach North":67.6,"Paraparaumu Beach West":64.8,"Waikanae Park":71.6,"Otaihanga":75,"Paraparaumu North":67.9,"Otaki Forks":78.4,"Maungakotukutuku":71.4,"Raumati Beach West":68.9,"Raumati South":69,"Paekakariki":64.2,"Pukerua Bay":71.3,"Paekakariki Hill":85.7,"Plimmerton":60,"Titahi Bay North":27.9,"Titahi Bay South":26.3,"Elsdon-Takapuwahia":15.4,"Pauatahanui":76.9,"Onepoto":33.1,"Camborne":61,"Paremata":57.5,"Gore South":80.5,"Otatara":73.2,"Pakaraka":53.8,"Ascot Park":17.7,"Endeavour West":69,"Cannons Creek North":4.8,"Waitangirua Tairangi":8.4,"Cannons Creek East":4.1,"Akatarawa":73.8,"Riverstone Terraces":56.7,"Heretaunga":59.8,"Birchville-Brown Owl":65.5,"Totara Park":62.6,"Trentham South":46.2,"Wallaceville":51.1,"Pinehaven":74.8,"Kelson":59,"Belmont (Lower Hutt City)":57.1,"Petone Central":44.1,"Manor Park":51.9,"Taita South":25.4,"Hutt Central South":54.4,"Woodridge":37.9,"Wilton":63,"Wadestown":75.4,"Haruru":41.3,"Epuni West":38.6,"Woburn":50.5,"Waterloo West":44.9,"Naenae North":22.8,"Douglas Park":63.2,"Solway South":52.6,"Arakura":32.5,"Eastern Bays":80.8,"Pencarrow":56.4,"Glendale":30.2,"Eastbourne":84.3,"Homedale West":37.2,"Makara-Ohariu":80,"Karori South":62.9,"Tawa Central":52.4,"Grenada Village":40.6,"Pipitea-Kaiwharawhara":59.8,"Whareama":80.6,"Homebush-Te Ore Ore":72.1,"Mount Holdsworth":79.7,"Kokotau":77.4,"Gladstone (Carterton District)":62.5,"Tauherenikau":77.3,"Kahutara":71,"Aorangi Forest":71.1,"Paparangi":48,"Crofton Downs":65.2,"Johnsonville South":46.5,"Ngaio South":78.2,"Seatoun":72.6,"Kopuaranga":75.6,"Upper Plain":62.7,"Opaki":87,"Wellington Botanic Gardens":68.9,"Dixon Street East":58.5,"Vivian West":63.5,"Vivian East":57.7,"Solway North":54.8,"Kuripuni":58.1,"Invercargill Central":43,"Russell":63.6,"Mount Victoria North":70.6,"Roseneath":71.7,"Owhiro Bay":51.1,"Evans Bay":67,"Maupuia":44.8,"Island Bay East":64.8,"Miramar North":40.4,"Lyall Bay":59,"Karaka Bay-Worser Bay":74.3,"Houghton Bay":65,"Miramar South":41.9,"Golden Bay/Mohua":81,"Pohara-Abel Tasman":82.1,"Takaka Hills":80.7,"Kaiteriteri-Riwaka":49.5,"Upper Moutere":79.3,"Lower Moutere":61.2,"Motueka North":53.2,"Moutere Hills":85.6,"Waimea Inlet":83.3,"Ruby Bay":80,"Mapua":85.2,"Murchison-Nelson Lakes":79.2,"Waimea West":83.9,"Appleby (Tasman District)":68.1,"Wakefield Rural":85.5,"Richmond Central (Tasman District)":68.5,"Tuamarina":71.2,"Awatere":71.6,"Lower Wairau":77.8,"Woodbourne":73.5,"Spring Creek-Grovetown":62.7,"Wilkes Park":75.8,"Aniseed Valley":82.1,"Nelson Rural":78.7,"Marybank":77.1,"Britannia":51.8,"Broadgreen-Monaco":63.8,"Washington":52.7,"Nayland":64.8,"Aldinga":66.2,"Victory":50,"Omaio":63.6,"Marlborough Sounds West":69.5,"Marlborough Sounds East":77.4,"Upper Wairau":84.9,"Waikawa (Marlborough District)":64.6,"Waitohi (Marlborough District)":54.2,"Springlands":66.7,"Riversdale-Islington":50.3,"Redwoodtown West":57.7,"Riverlands":57.6,"Kaikoura Ranges":66.3,"Kaikoura":55.4,"Karamea":71.4,"Westport North":70.9,"Westport Rural":78.4,"Westport South":67.8,"Buller Coalfields":71.4,"Greymouth Central":57.9,"Whataroa-Harihari":67.9,"Hokitika Valley-Otira":71.4,"Hanmer Range":77.8,"Amuri":67.2,"Parnassus":70.7,"Ashley Forest":78.8,"Omihi":86.3,"Balcairn":77.6,"Amberley":78.4,"Okuku":88.9,"Yaldhurst":56.8,"Clearwater":82.9,"Woolston North":50,"New Brighton":68.3,"Cashmere West":82.8,"Ashgrove":78.7,"Oxford Estate":80,"Waikuku":81.3,"Southbrook":75,"Tuahiwi":66,"Pegasus Bay":71.1,"Belfast West":67.6,"Brooklands-Spencerville":62.5,"Styx":78.2,"Islington":52,"Marshland":66.7,"Burnside":52.6,"Avonhead East":55.8,"Sydenham Central":51.4,"Rawhiti":65.3,"Northcote (Christchurch City)":55.4,"Deans Bush":66.8,"Riccarton West":58.2,"Wigram East":37.5,"Sydenham West":65.6,"Levels Valley":86.4,"Geraldine":72.2,"Rangitata":75.9,"Waitohi (Timaru District)":71.4,"Hadlow":81.8,"Levels":78.9,"Riccarton South":51,"Halswell South West":54.5,"Riccarton East":60.8,"Christchurch Central-West":64.5,"Christchurch Central-North":61.6,"Gleniti North":79.7,"Washdyke":68.5,"Fairview":78.6,"Gleniti South":74.7,"Hoon Hay West":44.5,"Spreydon West":64.4,"Christchurch Central-East":62.2,"Halswell North":66.7,"Maungati":80.9,"Lyalldale":75,"Makikihi-Willowbridge":77.1,"Morven-Glenavy-Ikawai":54.4,"Chatham Islands":21.9,"Aviemore":79.2,"Somerfield East":72.2,"Linwood East":45.5,"Sydenham North":57,"Charleston (Christchurch City)":47.1,"Woolston West":58.6,"Brookhaven-Ferrymead":64.4,"Redcliffs":75,"Governors Bay":83.8,"Lyttelton":74.1,"Sumner":81.4,"Diamond Harbour":84.4,"Banks Peninsula South":79.7,"Banks Peninsula Eastern Bays":82.4,"Bankside":61.9,"Charing Cross":76.5,"Halkett":83.5,"Springston":76,"Rolleston South West":71,"Southbridge":75.4,"Irwell":78.7,"Ladbrooks":84.8,"Lindis-Nevis Valleys":80.1,"Manuherikia-Ida Valleys":81.8,"Earnscleugh":50,"Dunstan-Galloway":77.8,"Alexandra North":70.3,"Alexandra South":76.6,"Maniototo":70.7,"Teviot Valley":72.6,"Outer Wanaka":88.9,"Glenorchy":82.1,"Outer Wakatipu":87,"Cardrona":84.8,"Northlake":81.7,"Wanaka West":83.3,"Albert Town":84.5,"Wanaka Central":71.3,"Lincoln North":77.1,"Eiffelton":72.3,"Chertsey":67.7,"Winchmore-Wakanui":73.9,"Allenton South":71.1,"Ashburton North":80.4,"Tinwald South":69.4,"Arundel":80.8,"Glenwood":66.3,"Waimataitai-Maori Hill":58.9,"Seaview":60.9,"Watlington":66.2,"Timaru Central":52.4,"Mackenzie Lakes":50.6,"Opua (Mackenzie District)":87,"Hakataramea":83.7,"Arthurs Point":71.9,"Wakatipu Basin":81.2,"Warren Park":67,"Sunshine Bay-Fernhill":66.7,"Lake Hayes Estate":63.6,"Jacks Point":67.6,"Strath Taieri":81.1,"Bucklands Crossing":76.9,"Waikouaiti":65.8,"Wingatui":79.2,"Saddle Hill-Chain Hills":88.2,"Abbotsford":78.5,"Pine Hill-Dalmore":62.2,"Roseneath-Sawyers Bay":78.6,"North East Valley Knox":63.2,"Royal Terrace":65.4,"Maryhill":71,"Otago Peninsula":71,"Caversham":55.5,"Forbury":61.7,"Waverley (Dunedin City)":68.3,"Macandrew Bay-Company Bay":73,"Broad Bay-Portobello":77.1,"St Kilda South":60.6,"Andersons Bay":73.2,"West Otago":80.9,"Rosedale-Hargest":74.8,"Woodend-Greenhills":65.6,"Bluff":31.8,"Kaitaia West":12.8,"Rangitihi":27.6,"Oruru-Parapara":29.5,"Doubtless Bay":27.5,"Herekino-Takahue":27,"Peria":34.6,"Taemaro-Oruaiti":29.2,"Whakapaku":31,"Hokianga North":2.5,"Kohukohu-Broadwood":16.7,"Whakarara":18.3,"Kaeo":33.3,"Omahuta Forest-Horeke":24.6,"Kaitaia East":13.5,"Hokianga South":20,"Lake Manuwai-Kapiro":60.7,"Okaihau":46.8,"Rangitane-Purerua":47.5,"Kawakawa":12,"Mangakahia-Hukerenui":40.8,"Whangaruru":42.7,"Matarau":67.1,"Hikurangi":38.4,"Kamo Central":50.4,"Whau Valley":46.9,"Tikipunga North":33.5,"Pukenui":67.7,"Symonds Street North West":25.5,"Granfield Reserve":58.7,"Hatfields Beach":74.4,"Orewa South":75.5,"Millwater North":57.1,"Orewa Central":68.4,"Millwater Central":66.7,"Waipatukahu":69.6,"Otangarei":9,"Tikipunga South":33.5,"Kensington (Whangarei District)":41.5,"Abbey Caves-Glenbervie":68.7,"Mairtown":39.1,"Millwater South":51.7,"Milldale":60.2,"Dairy Flat North":68.8,"Murrays Bay West":47.3,"Tarewa":19.9,"Bayview East (Auckland)":30.8,"Onerahi Park":50,"Sherwood Rise":41.5,"Onerahi":40.3,"Parua Bay":61.4,"Bream Bay":57.4,"One Tree Point":56.4,"Ruakaka":41.5,"Bream Head":73.7,"Waipu":54,"Waipu Rural":63.1,"Kaipara Coastal":48.6,"Maungaru":66,"Dargaville":35.6,"Ruawai-Matakohe":53.3,"Otamatea (Kaipara District)":70.7,"Maungaturoto":56.2,"Kaiwaka":51.7,"Wellsford":51.2,"Kaukapakapa":73.4,"Kaukapakapa Rural":77.3,"Snells Beach":65.7,"Barrier Islands":58.8,"Mahurangi Peninsula":70.3,"Wainui-Waiwera":84.9,"Browns Bay South West":52.1,"Parakai":51.6,"Pinehill North":22.7,"Waitoki":83,"Orewa North":64.4,"Orewa West":56.3,"Dairy Flat West":78.6,"Kingsway":66,"Silverdale Central (Auckland)":41.9,"Red Beach West":65.1,"Red Beach East":76.2,"Silverdale South (Auckland)":74.3,"Wiri East":9.6,"Stanmore Bay West":74.1,"Kumeu Rural West":69.7,"Okura Bush":67.1,"Whangaparaoa Central":62.7,"Wade Heads-Arkles Bay":75,"Kumeu-Huapai North":59.9,"Goodwood Heights West":8,"Stanmore Bay East":67.1,"Manly West":67.8,"Muriwai Valley-Bethells Beach":74,"Tindalls-Matakatia":72.2,"Coatesville":77.3,"Dairy Flat South":70.7,"Awaruku":69.1,"Fairview Heights":27.6,"Pinehill South":17.7,"Forrest Hill North":37.6,"Massey Red Hills":40,"Forrest Hill East":43.1,"Glamorgan":63.7,"Oteha East":38,"Northcross":58.6,"Oteha West":22.4,"The Strand":31.4,"Waitakere":67,"Enderley North":22.8,"North Harbour":46.3,"Westgate South":27.9,"West Harbour West":33.5,"Unsworth Heights West":36.3,"Sunnynook South":27.4,"Totara Vale North":32.5,"Murrays Bay East":61.7,"Birdwood West":48.9,"Hobsonville Point Catalina Bay":61.1,"Hobsonville Point Park":49.8,"Hobsonville Scott Point":37.6,"West Harbour Clearwater Cove":48.8,"Unsworth Heights East":35.2,"Mairangi Bay North":61.2,"Royal Heights North":33,"Kelston South":5.9,"Mairangi Bay South":59.8,"Massey Royal Road West":22.3,"Massey West":22.1,"Totara Vale South":29.2,"Glenfield North":27.2,"Birkdale Central":47.1,"Rutland":81.2,"Glenfield West":32.7,"Ponsonby East":68.5,"Puhinui South":3.6,"Ranui Domain":17,"Ranui South West":21,"Te Atatu Peninsula Central":30.4,"Glenfield East":23,"Te Atatu Peninsula West":33.5,"Henderson Lincoln West":16.1,"Birkenhead West":53.4,"Birkenhead North West":59.8,"Hillcrest West (Auckland)":51.9,"Westlake":40.6,"Hillcrest North (Auckland)":40.8,"Te Atatu South-McLeod North":23.7,"Henderson Valley Park":17.5,"Henderson North East":17.9,"Waitakere Ranges South":63.3,"Northcote Tuff Crater":47.8,"Summerland South":23.6,"Summerland North":26.5,"Northcote Point (Auckland)":64.6,"McLaren Memorial Park":17.4,"Mount Albert South":59.2,"Hillcrest East (Auckland)":45.9,"Birkenhead North":46.9,"Henderson North":13,"Western Heights (Auckland)":28,"Te Atatu South-North":27.2,"Te Atatu South-Central":22.2,"Northcote South (Auckland)":46.4,"Waiatarua":62.8,"Henderson East":21.7,"Te Atatu South-McLeod South":26.5,"Takapuna South":61.9,"Hauraki":62.9,"Symonds Street West":17.3,"Glen Eden West":27.4,"Glen Eden Woodglen":29.2,"Glen Eden Rosier":29.4,"Glen Eden Konini":45.8,"Ponsonby West":66.7,"Glen Eden North":24.3,"Wynyard-Viaduct":51.3,"Grey Lynn West":58.2,"New Lynn North":14.9,"Victoria Park":28.3,"Glen Eden Central":34.9,"Grey Lynn East":63.1,"Grey Lynn North":71,"Avondale North West (Auckland)":26.5,"Morningside (Auckland)":52.6,"Avondale North East (Auckland)":36.6,"Shortland Street":31.7,"Konini Road":61.5,"New Lynn North West":16.7,"Hobson Ridge North":26.7,"Grey Lynn Central":63.2,"Devonport":79,"Hobson Ridge South":24.8,"Avondale Central (Auckland)":23.4,"Queen Street":33.3,"Quay Street-Customs Street":27.7,"Hobson Ridge Central":16.1,"Cheltenham":77.3,"Anzac Avenue":29.4,"Waima-Woodlands Park":72.7,"Awapuni North":44.3,"Mount Albert Central":51.7,"Karangahape East":39.8,"Kingsland":63.1,"Kaurilands":62.2,"Auckland-University":23.5,"New Lynn Seabrook":22.6,"Titirangi East":47.5,"New Lynn Central South":14.7,"St Lukes":39.1,"Symonds Street East":30.8,"Eden Terrace":43.9,"Grafton West":40,"Mount Eden East":56.7,"Grafton":43.6,"Sandringham North":53.4,"Wesley East":9,"Parnell West":49.8,"New Lynn South East":24.2,"Mount Eden South":57.9,"Owairaka East":30.9,"Eden Valley":56.2,"Sandringham Central":35,"Glenavon":10.5,"Blockhouse Bay Central":24.8,"Green Bay North":39.5,"Epsom Central-North":32.1,"Sandringham West":40.9,"Mount Eden North East":31.4,"Mount Eden North":56,"Wesley West":9,"Balmoral":53.1,"Sandringham East":35.2,"New Windsor South":15,"New Windsor East":12,"Newmarket":24.4,"Blockhouse Bay North East":15.8,"Epsom North":36.4,"Broken Run":44.7,"Blockhouse Bay East":22.1,"St Albans East":66.1,"Mount Roskill North":39.4,"Mount Roskill White Swan":16.2,"Mount Roskill Nirvana":12.4,"Mount St John":31,"Mount Roskill Central North":14.3,"Remuera North":63.4,"Mount Roskill North East":25.1,"Papatoetoe North East":6.7,"Mount Roskill Central South":7.6,"Epsom Central-South":41.5,"Lynfield Central":16.8,"Remuera South":49.5,"Three Kings North":54.9,"Mount Roskill South":25.2,"Otara South West":1.3,"Epsom East":46.2,"Remuera Waiata":64.6,"Epsom South":48.6,"Kohimarama Bay":71.4,"Stonefields West":50.5,"Kohimarama Stadium":75.2,"Meadowbank West":60,"Three Kings South":22.2,"Onehunga Central":32.8,"Hillsborough North (Auckland)":29.7,"Mount Roskill Central East":20.3,"Greenlane North":38.2,"Mount Roskill South East":13.3,"Waikowhai Bay":26.1,"One Tree Hill Oranga":42.4,"Meadowbank East":60.2,"One Tree Hill Amaru":48.1,"Hillsborough Central (Auckland)":19.6,"Sunnyhills East":31.9,"Ellerslie Central":52.6,"Royal Oak East (Auckland)":36,"Saint Heliers South":60.9,"Onehunga North":33.9,"Saint Johns West":51.9,"Tareha Reserve":59,"Remuera Waiatarua":48.5,"Hilltop (Auckland)":8.2,"Ellerslie East":47.9,"Saint Johns East":37.4,"Wiri North":3.5,"Glen Innes West":24.3,"Ellerslie South":49.1,"Glendowie South West":58.1,"Oranga":17,"Mount Wellington North West":34.1,"Rongomai West":2.3,"Te Papapa":30.8,"Chapel Downs":6.6,"Wiri West":11.7,"Stonefields East":49.5,"Mount Wellington North East":33.8,"Mount Wellington Ferndale":22,"Point England South":13.9,"Mount Wellington East":25.2,"Mount Wellington West":23.4,"Panmure West":15.4,"Tamaki West":14.9,"Clover Park North":1.7,"Mangere Mountain View":13.4,"Surfdale":59.8,"Bucklands Beach Central":27.4,"Mangere North":5.1,"Favona West":3.5,"Ostend":65.9,"Half Moon Bay North East":28.2,"Mangere West":1.6,"Pakuranga West":20.9,"Half Moon Bay South East":28.4,"Bucklands Beach Murvale":20.2,"Harania South":1.7,"Highland Park (Auckland)":30.6,"Otahuhu South West":10.9,"Harania North":0.8,"Pakuranga Heights South West":22.7,"Otahuhu Central":7.6,"Mangere Central":1.3,"Mangere South East":3.3,"Otahuhu North East":4.5,"Pakuranga Heights North West":30.8,"Otahuhu East":12.6,"Mangere South":2.5,"Clover Park East":0.9,"Mangere Mascot":1.4,"Waiheke East":64,"Massey Road West":1.4,"Otahuhu South":8.2,"Aorere Central":2.7,"Northpark North":44.7,"Botany Downs West":39.3,"East Tamaki":33.3,"Howick East":54.3,"Burswood":20.2,"Botany Downs East":45.6,"Grange":3.1,"Golflands":38.1,"Aorere North":0.8,"Mangere East":4.5,"Somerville":43.2,"Northpark South":33,"Dingwall":3.4,"Papatoetoe North West":3.5,"Papatoetoe North":4.8,"Papatoetoe Central West":8.5,"Aorere South West":3.7,"Aorere South East":3.4,"Huntington Park":30.8,"Dannemora North-Shamrock Park":32.3,"Papatoetoe Central East":4.9,"Redcastle":23,"Dannemora South":28.8,"Armoy":21.5,"Otara East":1.5,"Otara South":1.9,"Ormiston Central":9.7,"Ferguson":1.8,"Papatoetoe South West":2.9,"Ormiston South":5.8,"Middlefield":22.3,"Point View":29.1,"Puhinui North":5.8,"Savonna":16.1,"Baverstock":14.2,"Puhinui East":4.2,"Ormiston North":11.3,"Maraetai":79.2,"Mission Heights North":14.6,"Clover Park South":3,"Donegal Park West":8.5,"Donegal Park East":5.5,"Ormiston East":5.5,"Totara Heights":13,"Homai West":3.1,"Homai Central":4.6,"Bremner Ridge":7.8,"Ormiston South East":12.8,"Takanini McLennan":15.9,"Tuscany Heights":26.1,"Papakura North":16.5,"Pahurehure":35.6,"The Gardens (Auckland)":26.2,"Hillpark North":16.5,"Papakura Central":22.5,"Terrace End":48.3,"Clendon Park East":2.1,"Rowandale East":3.2,"Manurewa Central":5.2,"Whangamata East":57.3,"Miranda-Pukorokoro":45.9,"Hauraki Plains North":62.9,"Hauraki Plains East":68.6,"Weymouth West":5.7,"Weymouth Central":3.6,"Papaioea South":53.9,"Hillpark South":15.8,"Alfriston":12.9,"Leabank":4.2,"Manurewa South":4.7,"Randwick Park West":5.4,"Kingseat-Karaka":57.4,"Takanini North":8.9,"Conifer Grove West":36.7,"Conifer Grove East":15.3,"Takanini West":8.5,"Takanini South":9.6,"Hingaia":35.7,"Takanini South East":13.5,"Papakura North East":16.5,"Twin Parks Rise":12.2,"Papakura Kelvin":11.2,"Taitoko":30.3,"Papakura Eastburn":8.8,"Papakura Massey Park":14.4,"Rosehill":18.6,"Patumahoe":74.2,"Papakura East":8.7,"Harbour View Heights":36.8,"Opaheke":32.3,"Red Hill":13.4,"Runciman":48.9,"Drury South Crossing":48.1,"Waihoehoe":52.4,"Waiuku Central":55.1,"Waiuku East":52.7,"Kendallvale":67.3,"Puni":56.7,"Hunua":64.5,"Pukekohe North":43.8,"Pukekohe North West":19.2,"Anselmi Ridge":58.5,"Pukekohe West":30.2,"Pukekohe South West":39,"Cape Hill":66.7,"Rosa Birch Park":51.9,"Pukekohe Central":37.5,"Pukekohe Hospital":58,"Buckland":55.4,"Bombay Hills":65.3,"Colville":25.5,"Coromandel":38.6,"Mercury Bay North":77.1,"Whitianga North":65.2,"Whitianga South":60.9,"Whitianga Waterways":62.5,"Thames Coast":47.5,"Mercury Bay South":80.6,"Kauaeranga":68.2,"Thames North":46.3,"Thames Central":43.2,"Thames South":45.5,"Totora-Kopu":54.1,"Tairua":64.4,"Pauanui":76.5,"Matatoki-Puriri":69.1,"Whangamata Rural":65,"Whangamata West":62.5,"Ngatea":68.5,"Hauraki Plains South":55.3,"Paeroa Rural":61.3,"Paeroa":43.7,"Waihi Rural":62.5,"Waihi North":46.8,"Tuakau South":38.1,"Pokeno North":39.8,"Pokeno South":36.2,"Te Aroha West":57.3,"Waihou-Manawaru":68.1,"Te Kauwhata West":52.5,"Te Uku":63.9,"Whale Bay":58.7,"Taupiri-Lake Kainui":54.5,"Ngaruawahia North":27.7,"Ngaruawahia Central":30.7,"Waitoa-Ngarua":53.8,"Richmond Downs-Wardville":58,"Waharoa-Peria":43.6,"Okauia":74.2,"Hinuera":73.8,"Ngaruawahia South":30.1,"Matamata North":62.9,"Kainui-Gordonton":60.6,"Matamata West":61.4,"Te Kowhai":68.9,"Whatawhata West":61.5,"Horotiu":55.3,"Rotokauri":70.2,"Matamata East":69.4,"Eureka-Tauwhare":72,"Morrinsville North":68.5,"Morrinsville West":56,"Te Manatu":43.2,"Te Aroha East":49.5,"Forest Lake (Hamilton City)":46.4,"Flagstaff North West":45.3,"Flagstaff North East":39.3,"Burbush-Baverstock":37.7,"Pukete West":45,"Kihikihi Central":55.3,"Flagstaff East":50.5,"Rototuna West":49.2,"Rototuna East":48.1,"Pukete East":55.5,"Paraonui":30.5,"Saint Andrews East":54.4,"Queenwood (Hamilton City)":59.9,"Porritt":30.5,"St James":55.6,"Crawshaw":28.7,"Matarawa":21.7,"Western Heights (Hamilton City)":42.5,"Stanley Park":24.8,"Nawton West":35.2,"Nawton East":31.8,"Hairini":49,"Chedworth":46.6,"Fairfield North (Hamilton City)":27.3,"Pyes Pa East":39.5,"Te Maunga South":59.2,"Dinsdale North":40.6,"Dinsdale South":45.5,"Fairview Downs":37.5,"Temple View":14.1,"Swarbrick":31.7,"Enderley South":26.1,"Kahikatea":36,"Kirikiriroa":38.7,"Greenhill Park":35,"Hillcrest East (Hamilton City)":39,"Hamilton Central":47.1,"Hamilton Lake North":38.2,"Hamilton Lake South":45.2,"Peachgrove":36.6,"Hamilton East Village":42.9,"Hamilton West":40.6,"Melville North":31.3,"Leamington Central":70.3,"Deanwell":37.4,"Hillcrest West (Hamilton City)":46,"Hei Hei":47.8,"Resthill":44.3,"Fitzroy (Hamilton City)":36.2,"Riverlea":52.4,"Peacocke":50,"Te Pahu":72.7,"Ngahinapouri":72.5,"Lake Cameron":70.7,"Lake Ngaroto":72.1,"Kaipaki":71.4,"Pirongia":77.6,"Te Awamutu Central":63.6,"Pekerau":58,"Hautapu Rural":77.8,"Te Rahu":73,"Fencourt":88.1,"Fraser Street":56.4,"Sherwin Park":50.8,"St Leger":69.2,"Rotoorangi":72.5,"Tokanui":39.4,"Oaklands-St Kilda":75.3,"Te Awamutu North":62.9,"Te Awamutu West":61.1,"Leamington South":77.3,"Leamington East":76.1,"Te Awamutu Stadium":61.7,"Bexley":46.9,"Te Kuiti West":22.6,"Mangapapa North":29.2,"Te Kuiti East":17.5,"Waipa Valley":44,"Marotiri":43.3,"Mangakino":27.8,"Ohakuri":61.4,"Lake Taupo Bays":38.2,"Mapara":77.8,"Kinloch":78.8,"Wairakei-Broadlands":52.8,"Acacia Bay":72.5,"Brentwood (Taupo District)":53.9,"Mountview":37.1,"Elgin":17.4,"Hilltop (Taupo District)":50,"Invergarry":42.9,"Waipahihi":60,"Waihi Beach-Bowentown":64.3,"Tahawai":63.4,"Athenree":55.2,"Aongatete":65.1,"Katikati North":54.6,"Katikati South":40.3,"Pahoia West":75,"Pahoia East":76.1,"Omokoroa North":71.6,"Minden":70.7,"Kaimai":71.8,"Kopurererua":84.2,"Keenan Road":57.9,"Waitao":56.8,"Waiorohi":74.3,"Otawa":59.2,"Te Puke West":29.3,"Te Puke East":27.4,"Matua South":61.8,"Bethlehem North":49.6,"Bellevue":61.5,"Otumoetai North":70.1,"Te Hapara South":21.7,"Otumoetai South":68.8,"Brookfield West":52.2,"Bethlehem Central":67.9,"Doncaster":43.5,"Te Reti":47.5,"Pacific Lakes":62.1,"Kaitemako":54.2,"Bethlehem South":76.2,"Ohauiti":63.7,"Baypark-Kairua":28,"Tauriko":70.6,"Fraser Cove":33.3,"Matapihi":6.5,"Pyes Pa North West":52.4,"Welcome Bay West":53.7,"Pyes Pa West":53.8,"Pukehangi North":20.1,"Koutu":13.9,"Arataki South":57.2,"Pyes Pa South":59.2,"Poike":50.5,"Te Maunga North":52.4,"Maungatapu":55,"Welcome Bay South":52.3,"Springfield South":45.7,"Springfield North":45.9,"Mangapapa East":37.5,"Wairakei West":39.2,"Wairakei Central":58.2,"Wairakei East-Te Tumu":52.2,"Tui Ridge":66,"Mangapapa South":26.1,"Te Hapara East":24.6,"Centennial Crescent":14.3,"Whataupoko East":50,"Whataupoko West":46.7,"Gisborne Central":17.6,"Kaiti North":31,"Ngongotaha Valley":49,"Hamurana":55.6,"Ngongotaha East":29.1,"Ngongotaha West":38.1,"Ngongotaha South":34.6,"Selwyn Heights":22.7,"Kaiti South":12.8,"Pleasant Heights":21.9,"Fairy Springs":26.9,"Western Heights (Rotorua District)":20.3,"Mangakakahi West":23.4,"Sunnybrook":41.5,"Waiohewa":43.6,"Glenholme North":16,"Ngapuna":0,"Fenton Park":12.1,"Lynmore":59.1,"Tihiotonga-Whakarewarewa":22.9,"Matata-Otakiri":40,"Onepu Spring":37.9,"Edgecumbe":36.8,"Te Teko Lakes":9.2,"Papanui North":47.9,"Trident":23,"Allandale":31.8,"Redwood East":63.4,"Mokorua Bush":61.8,"Waingarara-Waimana":12.6,"Murupara":3.5,"Monika Reserve":17.4,"Tarawera Park":16.2,"Woodlands":29.2,"East Cape":4.7,"Waipaoa":33.3,"Ruatoria-Raukumara":2.3,"Tokomaru":7.8,"Hangaroa":45.5,"Wharekaka":19.5,"Te Arai":17.1,"Hexton":56.3,"Lytton":45,"Makaraka-Awapuni":25,"Riverdale":34.2,"Waltham":57.2,"Outer Kaiti":6.5,"Tamarau":12,"Wainui-Okitu":60.5,"Omahu-Pakowhai":33.7,"Frimley":51.1,"Bridge Pa":16,"Twyford":36.7,"Poukawa":66.7,"Flaxmere West":9.7,"Omahu Strip":26.3,"Flaxmere Park":12.7,"Irongate":37.5,"Camberley":18.1,"Mahora":45,"Raureka":31.6,"Cornwall Park":42.1,"Tomoana":21.7,"Raceway Park":38.4,"Hastings Central":29.7,"Tomoana Crossing":49.1,"Taradale West":75,"Akina Park":49.3,"Maraenui":20.3,"Mayfair":31.5,"Parkhaven":50.5,"Parkvale":55.8,"Stratford North":70.3,"Te Awanga":76.9,"Lucknow":38.2,"Greenmeadows Central":67.6,"Karanema-St Hill":70.5,"Nelson Park":52.7,"Bledisloe Park":62.2,"Brookvale":78.7,"Iona":73.4,"Te Mata Hills":89.1,"Havelock Hills":76.8,"Pirimai East":46,"Ahuriri":46.8,"Onekawa East":31.9,"Greenmeadows West":71.8,"Hospital Hill":67.9,"Tamatea West":52.9,"Tamatea North":46.3,"Taradale Central":61.9,"Tamatea East":48.4,"Marewa West":59.4,"Napier Central":30,"Greenmeadows South":57.5,"McLean Park":57.4,"Waipawa":53.8,"Hawera West":60.2,"Waipukurau West":48.4,"Moturoa":61.4,"Normanby (South Taranaki District)":43.1,"Tawhiti":66.7,"Ohangai":74.2,"Turuturu":55.4,"Blagdon-Lynmouth":54.3,"King Edward Park":46.6,"Ramanui":46,"Marfell":40.1,"Whalers Gate":63.9,"Strandon":62,"Westown":54.9,"Bell Block West":48.9,"Bell Block Central":47.6,"Bell Block East-Puketapu":58.5,"Lower Vogeltown":64.8,"Hurdon":72.4,"Frankleigh Park":68.1,"Merrilands":59.2,"Ferndale":75,"Welbourn":62.4,"Fitzroy (New Plymouth District)":61.2,"Glen Avon":64.6,"Waitara West":37.1,"Upper Vogeltown":71.4,"Highlands Park (New Plymouth District)":71.3,"Paraite":74.5,"Waitara East":36.2,"Lepperton-Brixton":58.1,"Mangorei":79.6,"Mount Messenger":62.2,"Stratford Central":63.2,"Stratford South":65.3,"Parihaka":58.9,"Taungatara":67.5,"Opunake":43.2,"Kaponga-Mangatoki":70.4,"Manaia":39.3,"Kapuni":67.6,"Eltham":57.1,"Okaiawa":68.7,"Te Roti-Moeroa":75.6,"Taumarunui Central":26.5,"Taumarunui East":16,"National Park":66.1,"Tangiwai":50,"Raetihi":26.2,"Ohakune":38.5,"Waiouru":47.1,"Upper Whanganui":45.3,"Otamatea (Whanganui District)":73.2,"Springvale North":78.9,"Castlecliff East":38,"Palmerston North Hospital":57.5,"St Johns Hill East":62.2,"St Johns Hill West":62.4,"Titoki":36,"Springvale East":53.2,"College Estate":56,"Gonville West":32,"Gonville North":49.1,"Whanganui Central":41.7,"Gonville South":51.6,"Bastia-Durie Hill":62,"Putiki":45.7,"Mokai Patea":60.8,"Turakina":40.6,"Otairi":62.7,"Taihape":25.6,"Marton Rural":74.5,"Roslyn (Palmerston North City)":44.4,"Marton North":56,"Marton South":47.5,"Ohakea-Sanson":73.9,"Kelvin Grove West":50.7,"Mount Taylor":75,"Makino":55.3,"Feilding Central":61.8,"Kelvin Grove North":63.2,"Milson North":55.8,"Cloverlea (Palmerston North City)":49.3,"Milson South":46.5,"Highbury East":32.8,"Park West":46,"Takaro South":52.3,"Papaioea North":52.7,"Palmerston North Central":48.8,"Royal Oak (Palmerston North City)":55.2,"West End":49.6,"Awapuni South":58.2,"Milverton":58.2,"Esplanade":49.5,"Ruamahanga":60.6,"Fitzherbert":44.2,"Norsewood":65,"Papatawa":63.8,"Mangatainoka":66.7,"Hokowhitu Central":63.2,"Hokowhitu East":59.5,"Ruahine":62.5,"Hokowhitu South":53.9,"Poutoa":59.4,"Woodville":51.1,"Dannevirke West":47.9,"Dannevirke East":40,"Waitahora":65.7,"Kaitawa":66.7,"Pahiatua":57,"Nireaha-Eketahuna":66.3,"Owahanga":71.9,"Kere Kere":58.9,"Foxton Beach":57.3,"Wainuiomata Central":35,"Foxton North":40.2,"Foxton South":41,"Waitarere":58.8,"Waikawa (Horowhenua District)":58.1,"Miranui":59.6,"Donnelly Park":39.7,"Ohau-Manakau":59,"Kawiu South":44.4,"Levin Central":29.7,"Shannon":36.6,"Queenwood (Horowhenua District)":37.8,"Playford Park":38.5,"Fairfield (Horowhenua District)":45.2,"Tararua":44.9,"Waitohu":46.5,"Paraparaumu Beach East":64.5,"Waikanae West":64.2,"Waikanae East":68,"Paraparaumu Central":55.3,"Taita North":15.4,"Boulcott":49.3,"Raumati Beach East":63.2,"Paraparaumu East":58.9,"Porirua Central":32.4,"Papakowhai":48.4,"Aotea":39.5,"Postgate":45.9,"Whitby":61.3,"Porirua East":11.5,"Hope":69.4,"Endeavour East":62,"Waitangirua Corinna":3.2,"Ranui Heights":20,"Cannons Creek South":6.4,"Poets Block":49.3,"Brentwood (Upper Hutt City)":47.4,"Hutt Central North":40.5,"Avalon West":32.1,"Silverstream (Upper Hutt City)":70.2,"Maoribank":51,"Te Marua":66.7,"Elderslea":51.6,"Trentham North":53.2,"Ebdentown":54.1,"Clouston Park":51.3,"Upper Hutt Central":53.6,"Maungaraki":54.7,"Korokoro":66.7,"Normandale":65.4,"Stokes Valley Central":37.1,"Tirohanga":64.9,"Alicetown-Melling":49.7,"Petone East":48.4,"Stokes Valley North":44.2,"Petone Esplanade":46,"Avalon East":26.6,"Waiwhetu North":37.5,"Naenae Central":23.5,"Naenae South":21.7,"Ben Cooper Park":72.1,"Epuni East":39.5,"Moera":24.3,"Delaney":33.5,"Waiwhetu South":40,"Waterloo East":53.5,"Manuka":47.4,"Wainuiomata West":35.7,"Homedale East":40.6,"Tawa North":42.6,"Linden":38.9,"Tawa South":58.3,"Grenada North":55.6,"Richmond South (Tasman District)":82.1,"Churton Park North":42.8,"Glenside-Churton Park East":50,"Churton Park South":46.9,"Grampians":57.4,"Johnsonville West":44.4,"Newlands East":40.5,"Johnsonville North":49.5,"Avonhead South":57.4,"Ngaio North":72.5,"Riccarton Racecourse":50.3,"Johnsonville Central":42.8,"Broadmeadows":48.4,"Hornby South":46.6,"Khandallah Reserve":69.3,"Prestons":72,"Karori Park":55.2,"Karori West":52.9,"Bromley South":51.8,"Newlands North":44.2,"Karori North":71.8,"Newlands South":51.5,"Khandallah North":69.5,"Khandallah South":67.2,"Ensors":63.1,"Onslow":62.5,"Karori East":71.2,"Northland (Wellington City)":71.7,"Thorndon North":67.5,"Thorndon South":63.4,"Kelburn":75.2,"Wellington Central":58.7,"Aro Valley":70.9,"Wellington University":70.6,"Brooklyn North":70.5,"Dixon Street West":63.7,"Courtenay":58,"Brooklyn East":70.9,"Mount Cook North":62.7,"Mount Cook South":70.2,"Brooklyn South":62,"Newtown North":58,"Oriental Bay":70.1,"Mount Cook East":63.4,"Mount Victoria South":70.7,"Kingston-Mornington-Vogeltown":65.2,"Newtown West":63.9,"Hataitai North West":73.1,"Hataitai North East":71.5,"Kilbirnie East":36.4,"Berhampore":58.7,"Hataitai South":73.8,"Newtown South":53.5,"Miramar East":64.3,"Kilbirnie Central":60.5,"Island Bay West":65.2,"Melrose":70.2,"Miramar Central":42.7,"Strathmore (Wellington City)":39.9,"Southgate":57.1,"Ngaumutawa":54.2,"Lansdowne West":59.6,"McJorrow Park":23,"Masterton Central":63.2,"Carterton North":60.5,"Lansdowne East":56.4,"Carterton South":63.7,"Cameron and Soldiers Park":51.9,"Featherston":58.7,"Greytown":71.6,"Martinborough":53,"Wakefield":85.7,"Takaka":78.6,"Motueka West":55.6,"Motueka East":63.7,"Golden Downs":78.4,"Richmond West (Tasman District)":74.4,"Brightwater":81.3,"Templemore":85.2,"Easby Park":74.1,"Fairose":78.3,"Tahunanui":57.2,"Redwoodtown East":54.6,"Atawhai":75.2,"Maitlands":74.3,"Tahuna Hills":65.4,"Nelson Central-Trafalgar":52.6,"The Wood":60.3,"Toi Toi":43.5,"Rutherford":70.8,"Maitai":68.3,"Suffolk":69.3,"Enner Glynn":68.6,"Daelyn":85.2,"The Brook":71.1,"Witherlea East":67.7,"Charleston (Buller District)":75,"Inangahua":75.6,"Renwick":73.8,"Reefton":59.5,"Barrytown":77.3,"Runanga":76,"Cobden":71.1,"Yelverton":58.9,"Ashley Gorge":78.9,"Oxford":85.4,"Mayfield":54,"Whitney West":58.3,"Starvation Hill-Cust":86.1,"Loburn":83.2,"Eyrewell":74,"West Eyreton":82.7,"Ashley-Sefton":82.8,"Fernside":84.1,"Burleigh":62.7,"Lilybrook":72.8,"Blenheim Central":55.3,"Whitney East":55.1,"Witherlea West":67.7,"Prestons Park":67.2,"Blaketown":74.5,"Sovereign Palms":74.4,"King Park":70.3,"Marsden":75.4,"Karoro":80.4,"Rutherglen-Camerons":87,"Greymouth Rural":83.3,"Dobson":80.4,"Nelson Creek":80,"Lake Brunner":88.7,"Westland Glaciers-Bruce Bay":55.2,"Arahura-Kumara":64.7,"Hokitika":58.1,"Hokitika Rural":76.8,"Waitaha":73.7,"Hanmer Springs":57.1,"Upper Hurunui":75.4,"Rangiora North West":80.2,"Kaiapoi West":66.2,"Kingsbury":82,"Rangiora North East":77.7,"Strowan":73.1,"Rangiora South West":82.6,"Ravenswood":75.6,"Waikuku Beach":76.9,"Fendalton":69.3,"Mandeville":86.7,"Ohoka":86.3,"Rangiora South East":75,"Swannanoa-Eyreton":87.5,"Silverstream (Waimakariri District)":64.8,"Woodend":74.3,"Pegasus":77.7,"Clarkville":82.6,"Kaiapoi North West":66.1,"Kaiapoi Central":71.7,"Paparua":45,"Kaiapoi South":73.9,"Avonhead West":52.8,"Harewood":69,"Bishopdale South":59.6,"Belfast East":61.3,"Northwood":67.2,"Burnside West":52.8,"Regents Park":76.3,"Russley":60.1,"Bishopdale North":63,"Casebrook":65.4,"Bishopdale West":61,"Templeton":66.7,"Burnside Park":57.1,"Avonhead North":59.8,"Redwood North":69.6,"Broomfield":40.9,"Redwood West":60.7,"Bryndwr North":53.8,"Papanui West":67.2,"Ilam North":67.5,"Hornby West":41.7,"Jellie Park":63,"Ilam South":65,"Bryndwr South":59.9,"Papanui East":64.6,"Sockburn North":52.6,"Branston":54,"Ilam University":72.1,"Waitikiri":76.8,"Malvern":69.9,"Mairehau North":65.1,"Bush Inn":66.2,"Awatea North":41.3,"Upper Riccarton":59.8,"Sockburn South":50,"Wigram North":51.1,"Holmwood":80,"Wharenui":58.5,"Wigram West":35,"Awatea South":36.7,"Merivale":75.1,"Mairehau South":67.1,"Oaklands West":57.5,"Mona Vale":62.5,"Shirley East":67.1,"Shirley West":51.7,"Middleton":47.7,"Wigram South":37,"Queenspark":70.8,"St Albans North":70.6,"St Albans West":67,"Burwood North":74.8,"Halswell West":53.2,"Hillmorton":58.7,"Parklands":63.1,"Edgeware North":66.9,"Edgeware South":62,"Addington West":43.5,"Aidanfield":52.6,"Burwood South":64.3,"Oaklands East":64.5,"Richmond North (Christchurch City)":60.1,"Christchurch Central-South":62.9,"Waimairi Beach":84.4,"Spreydon North":62.7,"Dallington":60.8,"Richmond South (Christchurch City)":57,"North Beach":67.4,"Wainoni":51,"Addington East":56.6,"Avondale (Christchurch City)":61.4,"Linwood North":46.6,"Hoon Hay East":69.2,"Aranui":39.9,"Avonside":49.6,"Stanmore":42.9,"Linwood Central":41.9,"Halswell South":71,"Spreydon South":64.9,"Lancaster Park":35,"Phillipstown":47.6,"Kennedys Bush":81.6,"Halswell South East":75,"Sydenham South":63.9,"Somerfield West":72.9,"Hoon Hay South":74.8,"Westmorland":76.2,"Beckenham":80,"Opawa":79.4,"St Martins":69.9,"Burnham Camp":65.1,"Woolston East":48.3,"Huntsbury":79.7,"Rolleston North Central":62.8,"Cashmere East":82.4,"Rolleston Central":68.2,"Hillsborough (Christchurch City)":73.2,"Rolleston Tauwharekakaho":64.5,"Woolston South":53.3,"South New Brighton":69,"Heathcote Valley":78.3,"Rolleston North East":61.2,"Rolleston South Central":68.3,"Faringdon":57.5,"Mount Pleasant":79.9,"Rolleston South East":59.2,"Clifton Hill":85.2,"Akaroa Harbour":75,"Akaroa":68.4,"Torlesse":75.5,"Glenroy-Hororata":77.5,"Glentunnel":82.9,"Darfield":85,"Netherby":52.3,"Kirwee":89.1,"Kensington (Timaru District)":68.3,"Newtons Road":76.9,"West Melton":82.9,"Trents":78.2,"Prebbleton North":81.1,"Prebbleton South":79.4,"Lincoln West":68.9,"Seddon Park":69.6,"Lincoln South":69.6,"Lincoln East":80,"Leeston":73,"Tai Tapu":86.7,"Motukarara":81.3,"Cairnbrae":67.1,"Ashburton Forks":68.8,"Methven":76.1,"Ealing-Lowcliffe":65.7,"Allenton North":64.1,"Rockdale":58,"Rakaia":69.4,"Strathern":58,"Allenton East":59.8,"Winton":68.6,"Tinwald North":73.6,"Ashburton West":64.7,"Ashburton East":57.6,"Hampstead":55.2,"Normanby (Dunedin City)":69.4,"Pleasant Point":74.6,"Temuka West":67.9,"Temuka East":66.2,"Waimate North":72.7,"Marchwiel West":67.4,"Waimate East":77.2,"Danseys Pass":73.5,"Ngapara":70.5,"Lower Waitaki":70.4,"Waihemo":68.1,"Maheno":80.8,"Marchwiel East":66.7,"Queenstown Central":59,"Queenstown East":71.3,"Frankton Arm":65.5,"Frankton":50,"Kelvin Heights":75,"Campus West":58.4,"Highfield North":72.6,"Bush Road":74.8,"Highfield South":61.7,"Gore West":68.9,"Mataura":54.7,"West Plains-Makarewa":70.7,"Fraser Park":70.7,"Parkside":69.1,"Heidelberg":51.4,"Twizel":70,"Opoho":72.8,"Fairlie":71.7,"Campus North":65.2,"Campus South":60.6,"Waimate West":75.8,"Kingswell":58.6,"Weston":78.4,"Oamaru North Milner Park":61.5,"Oamaru North Orana Park":58.6,"Oamaru Gardens":67.3,"Glen Warren":42.6,"Waverley (Invercargill City)":65.8,"Richmond (Invercargill City)":57.2,"Holmes Hill":76.7,"South Hill":63.8,"Palmerston":69.4,"Mornington":63.5,"Cromwell West":69.6,"Cromwell East":67.5,"Mosgiel East":78.8,"Clyde":78.9,"Wanaka Waterfront":76.5,"Mosgiel Central":82.5,"Wanaka North":79.7,"Dunedin Central":54,"Lake Hawea":83,"Arrowtown":81.8,"Quail Rise":84.4,"Shotover Country":62.3,"Momona":81.8,"Taieri":80.3,"Mount Cargill":78.3,"East Taieri":75.9,"Concord":70.2,"Helensburgh":69.8,"Calton Hill":66.7,"Glenleith":65.8,"Glengarry":59.1,"Fairfield (Dunedin City)":77.6,"Turnbull Thompson Park":65,"Wakari":66.5,"Appleby North (Invercargill City)":44.9,"Brighton":75,"Kaikorai-Bradford":61,"Georgetown":51.7,"Maori Hill":72.8,"Corstorphine":60,"Roslyn (Dunedin City)":66.5,"North East Valley Chingford":60.2,"Belleknowes":68.1,"Newfield":62,"Gardens (Dunedin City)":68.9,"Kenmure":65.9,"Green Island":76.1,"South Dunedin":56.4,"Arthur Street":68.1,"Ravensbourne-St Leonards":75.2,"Fernhill":56.5,"Kew (Dunedin City)":68.6,"St Clair":72.3,"Musselburgh":59.5,"Shiel Hill":64.5,"St Kilda North":62,"Benhar-Stirling":80.8,"Kaitangata-Matau":68.5,"Fiordland":72.2,"Mararoa":84.6,"Te Anau":67.4,"Tainui":71.1,"Whitestone":82.4,"Mossburn":73.8,"Longwood Forest":70.6,"Ohai-Nightcaps":60.2,"Riversdale-Piano Flat":72.1,"Lumsden-Balfour":80.3,"Oreti River":77.5,"Otautau":67.3,"Hedgehope":75,"Balclutha South":63.5,"Balclutha North":68,"Prestonville-Grasmere":67.5,"Waikiwi":62.6,"Myross Bush":82.5,"Gladstone (Invercargill City)":64.8,"Avenal":63.2,"Windsor":60.8,"Appleby South (Invercargill City)":51.4,"Kennington-Tisbury":67.2,"Clifton-Kew":48.8}