{"Far North District":1.8,"Whangarei District":1.2,"Kaipara District":1.1,"Thames-Coromandel District":0.8,"Hauraki District":1,"Waikato District":1.5,"Matamata-Piako District":0.7,"Hamilton City":1.6,"Waipa District":0.7,"Ōtorohanga District":1.2,"South Waikato District":9.8,"Waitomo District":1.3,"Taupo District":1.1,"Western Bay of Plenty District":0.6,"Tauranga City":0.9,"Rotorua District":2.7,"Whakatane District":1.5,"Kawerau District":1.5,"Ōpōtiki District":1.9,"Gisborne District":1.2,"Wairoa District":1.4,"Hastings District":2.9,"Napier City":1.2,"Central Hawke's Bay District":1.5,"New Plymouth District":0.6,"Stratford District":0.6,"South Taranaki District":0.7,"Ruapehu District":1.6,"Whanganui District":1.2,"Rangitikei District":1.4,"Manawatu District":0.9,"Palmerston North City":1.4,"Tararua District":0.9,"Horowhenua District":1.4,"Kapiti Coast District":1,"Porirua City":6.6,"Upper Hutt City":1.5,"Lower Hutt City":2.1,"Wellington City":1,"Masterton District":1.2,"Carterton District":0.7,"South Wairarapa District":0.4,"Tasman District":0.3,"Nelson City":0.5,"Marlborough District":0.5,"Kaikoura District":0.2,"Buller District":0.3,"Grey District":0.4,"Westland District":0.4,"Hurunui District":0.2,"Waimakariri District":0.4,"Christchurch City":0.6,"Selwyn District":0.4,"Ashburton District":2.1,"Timaru District":0.4,"Mackenzie District":0.2,"Waimate District":0.3,"Chatham Islands Territory":2,"Waitaki District":0.4,"Central Otago District":0.3,"Queenstown-Lakes District":0.3,"Dunedin City":0.9,"Clutha District":0.5,"Southland District":0.4,"Gore District":1,"Invercargill City":1.7,"Auckland":3.2,"Area Outside Territorial Authority":0}